{"1":{"id":1,"mark":"条纹狼鲈-成年","fishId":101032110,"g":13233,"len":104,"exp":0,"price":15095,"hookDelay":200,"hookReelinDis":200,"minFightTime":15000,"escapeyDelay":5000},"2":{"id":2,"mark":"北美狗鱼-幼年","fishId":101032150,"g":6231,"len":95,"exp":0,"price":4753,"hookDelay":5000,"hookReelinDis":3000,"minFightTime":15000,"escapeyDelay":5000},"3":{"id":3,"mark":"白斑狗鱼-成年","fishId":101032170,"g":10854,"len":119,"exp":0,"price":12007,"hookDelay":8000,"hookReelinDis":8000,"minFightTime":25000,"escapeyDelay":5000},"4":{"id":4,"mark":"大口黑鲈-幼年","fishId":101032180,"g":5332,"len":70,"exp":0,"price":4279,"hookDelay":15000,"hookReelinDis":10000,"minFightTime":15000,"escapeyDelay":7000},"5":{"id":5,"mark":"条纹狼鲈-幼年","fishId":101032100,"g":6892,"len":84,"exp":0,"price":6508,"hookDelay":5000,"hookReelinDis":10000,"minFightTime":20000,"escapeyDelay":5000},"6":{"id":6,"mark":"鳄雀鳝-蓝标","fishId":101032230,"g":25336,"len":161,"exp":0,"price":98336,"hookDelay":20000,"hookReelinDis":8000,"minFightTime":35000,"escapeyDelay":5000},"7":{"id":7,"mark":"白斑狗鱼-幼年","fishId":101032170,"g":6110,"len":98,"exp":0,"price":3022,"hookDelay":20000,"hookReelinDis":10000,"minFightTime":15000,"escapeyDelay":5000},"8":{"id":8,"mark":"鳄雀鳝-蓝标","fishId":101032230,"g":60000,"len":212,"exp":0,"price":5013,"hookDelay":2000,"hookReelinDis":10000,"minFightTime":1000,"escapeyDelay":20000}}