{"5010001":{"id":5010001,"name":"buy_food_energy_bar_room","mark":"","showStyle":3,"itemType":202,"goodsId":102020001,"costItem":101,"costCount":300,"pondId":301020000},"5010002":{"id":5010002,"name":"buy_food_chips_room","mark":"","showStyle":3,"itemType":202,"goodsId":102020002,"costItem":101,"costCount":650,"pondId":301020000},"5010003":{"id":5010003,"name":"buy_food_chocolate_room","mark":"","showStyle":3,"itemType":202,"goodsId":102020003,"costItem":101,"costCount":1750,"pondId":301020000},"5010004":{"id":5010004,"name":"buy_food_canned_cornroom","mark":"","showStyle":3,"itemType":202,"goodsId":102020004,"costItem":101,"costCount":4000,"pondId":301020000},"5010005":{"id":5010005,"name":"buy_food_canned_room","mark":"","showStyle":3,"itemType":202,"goodsId":102020005,"costItem":101,"costCount":9000,"pondId":301020000},"5010006":{"id":5010006,"name":"buy_food_energy_bar_room","mark":"","showStyle":3,"itemType":202,"goodsId":102020001,"costItem":101,"costCount":300,"pondId":301020001},"5010007":{"id":5010007,"name":"buy_food_chips_room","mark":"","showStyle":3,"itemType":202,"goodsId":102020002,"costItem":101,"costCount":650,"pondId":301020001},"5010008":{"id":5010008,"name":"buy_food_chocolate_room","mark":"","showStyle":3,"itemType":202,"goodsId":102020003,"costItem":101,"costCount":1750,"pondId":301020001},"5010009":{"id":5010009,"name":"buy_food_canned_cornroom","mark":"","showStyle":3,"itemType":202,"goodsId":102020004,"costItem":101,"costCount":4000,"pondId":301020001},"5010010":{"id":5010010,"name":"buy_food_canned_room","mark":"","showStyle":3,"itemType":202,"goodsId":102020005,"costItem":101,"costCount":9000,"pondId":301020001},"5010056":{"id":5010056,"name":"buy_bait_mayfly","mark":"","showStyle":3,"itemType":305,"goodsId":1030510400101,"costItem":101,"costCount":8,"pondId":301020000},"5010057":{"id":5010057,"name":"buy_bait_fly","mark":"","showStyle":3,"itemType":305,"goodsId":1030510400201,"costItem":101,"costCount":8,"pondId":301020000},"5010058":{"id":5010058,"name":"buy_bait_bloodworm","mark":"","showStyle":3,"itemType":305,"goodsId":1030510400301,"costItem":101,"costCount":88,"pondId":301020000},"5010059":{"id":5010059,"name":"buy_bait_earthworm","mark":"","showStyle":3,"itemType":305,"goodsId":1030510400401,"costItem":101,"costCount":68,"pondId":301020000},"5010060":{"id":5010060,"name":"buy_bait_grasshopper","mark":"","showStyle":3,"itemType":305,"goodsId":1030510400501,"costItem":101,"costCount":8,"pondId":301020000},"5010061":{"id":5010061,"name":"buy_bait_minnow_1","mark":"","showStyle":3,"itemType":305,"goodsId":1030510600101,"costItem":101,"costCount":86,"pondId":301020000},"5010062":{"id":5010062,"name":"buy_bait_minnow_2","mark":"","showStyle":3,"itemType":305,"goodsId":1030510600102,"costItem":101,"costCount":88,"pondId":301020000},"5010063":{"id":5010063,"name":"buy_bait_minnow_3","mark":"","showStyle":3,"itemType":305,"goodsId":1030510600103,"costItem":101,"costCount":98,"pondId":301020000},"5010064":{"id":5010064,"name":"buy_bait_fish_cube_1","mark":"","showStyle":3,"itemType":305,"goodsId":1030511100101,"costItem":101,"costCount":18,"pondId":301020000},"5010065":{"id":5010065,"name":"buy_bait_fish_cube_2","mark":"","showStyle":3,"itemType":305,"goodsId":1030511100102,"costItem":101,"costCount":18,"pondId":301020000},"5010066":{"id":5010066,"name":"buy_bait_fish_cube_3","mark":"","showStyle":3,"itemType":305,"goodsId":1030511100103,"costItem":101,"costCount":18,"pondId":301020000},"5010067":{"id":5010067,"name":"buy_bait_salmon_roe","mark":"","showStyle":3,"itemType":305,"goodsId":1030511800101,"costItem":101,"costCount":168,"pondId":301020000},"5010068":{"id":5010068,"name":"buy_bait_shrimp","mark":"","showStyle":3,"itemType":305,"goodsId":1030510500101,"costItem":101,"costCount":428,"pondId":301020000},"5010069":{"id":5010069,"name":"buy_bait_crayfish","mark":"","showStyle":3,"itemType":305,"goodsId":1030510500201,"costItem":101,"costCount":198,"pondId":301020000},"5010070":{"id":5010070,"name":"buy_bait_clam_meat","mark":"","showStyle":3,"itemType":305,"goodsId":1030510500301,"costItem":101,"costCount":198,"pondId":301020000},"5010071":{"id":5010071,"name":"buy_bait_crayfish_tail_1","mark":"","showStyle":3,"itemType":305,"goodsId":1030511100201,"costItem":101,"costCount":235,"pondId":301020000},"5010072":{"id":5010072,"name":"buy_bait_crayfish_tail_2","mark":"","showStyle":3,"itemType":305,"goodsId":1030511100202,"costItem":101,"costCount":258,"pondId":301020000},"5010073":{"id":5010073,"name":"buy_bait_crayfish_tail_3","mark":"","showStyle":3,"itemType":305,"goodsId":1030511100203,"costItem":101,"costCount":268,"pondId":301020000},"5010074":{"id":5010074,"name":"buy_bait_meat_chunk_1","mark":"","showStyle":3,"itemType":305,"goodsId":1030511100301,"costItem":101,"costCount":328,"pondId":301020000},"5010075":{"id":5010075,"name":"buy_bait_meat_chunk_2","mark":"","showStyle":3,"itemType":305,"goodsId":1030511100302,"costItem":101,"costCount":368,"pondId":301020000},"5010076":{"id":5010076,"name":"buy_bait_meat_chunk_3","mark":"","showStyle":3,"itemType":305,"goodsId":1030511100303,"costItem":101,"costCount":388,"pondId":301020000},"5010077":{"id":5010077,"name":"buy_bait_honey_dough_1","mark":"","showStyle":3,"itemType":305,"goodsId":1030510900101,"costItem":101,"costCount":40,"pondId":301020000},"5010078":{"id":5010078,"name":"buy_bait_honey_dough_2","mark":"","showStyle":3,"itemType":305,"goodsId":1030510900102,"costItem":101,"costCount":55,"pondId":301020000},"5010079":{"id":5010079,"name":"buy_bait_honey_dough_3","mark":"","showStyle":3,"itemType":305,"goodsId":1030510900103,"costItem":101,"costCount":68,"pondId":301020000},"5010080":{"id":5010080,"name":"buy_bait_bread_1","mark":"","showStyle":3,"itemType":305,"goodsId":1030510900201,"costItem":101,"costCount":8,"pondId":301020000},"5010081":{"id":5010081,"name":"buy_bait_bread_2","mark":"","showStyle":3,"itemType":305,"goodsId":1030510900202,"costItem":101,"costCount":8,"pondId":301020000},"5010082":{"id":5010082,"name":"buy_bait_bread_3","mark":"","showStyle":3,"itemType":305,"goodsId":1030510900203,"costItem":101,"costCount":8,"pondId":301020000},"5010083":{"id":5010083,"name":"buy_bait_toast_1","mark":"","showStyle":3,"itemType":305,"goodsId":1030510900301,"costItem":101,"costCount":8,"pondId":301020000},"5010084":{"id":5010084,"name":"buy_bait_toast_2","mark":"","showStyle":3,"itemType":305,"goodsId":1030510900302,"costItem":101,"costCount":8,"pondId":301020000},"5010085":{"id":5010085,"name":"buy_bait_toast_3","mark":"","showStyle":3,"itemType":305,"goodsId":1030510900303,"costItem":101,"costCount":8,"pondId":301020000},"5010086":{"id":5010086,"name":"buy_bait_seeds","mark":"","showStyle":3,"itemType":305,"goodsId":1030510300101,"costItem":101,"costCount":235,"pondId":301020000},"5010087":{"id":5010087,"name":"buy_bait_niblet","mark":"","showStyle":3,"itemType":305,"goodsId":1030511000201,"costItem":101,"costCount":168,"pondId":301020000},"5010088":{"id":5010088,"name":"buy_bait_cheese_1","mark":"","showStyle":3,"itemType":305,"goodsId":1030511200101,"costItem":101,"costCount":168,"pondId":301020000},"5010089":{"id":5010089,"name":"buy_bait_cheese_2","mark":"","showStyle":3,"itemType":305,"goodsId":1030511200102,"costItem":101,"costCount":188,"pondId":301020000},"5010090":{"id":5010090,"name":"buy_bait_cheese_3","mark":"","showStyle":3,"itemType":305,"goodsId":1030511200103,"costItem":101,"costCount":198,"pondId":301020000},"5010091":{"id":5010091,"name":"buy_lure_shad01_1","mark":"","showStyle":3,"itemType":309,"goodsId":1030920100101,"costItem":101,"costCount":4500,"pondId":301020000},"5010092":{"id":5010092,"name":"buy_lure_shad01_2","mark":"","showStyle":3,"itemType":309,"goodsId":1030920100102,"costItem":101,"costCount":4500,"pondId":301020000},"5010093":{"id":5010093,"name":"buy_lure_shad01_3","mark":"","showStyle":3,"itemType":309,"goodsId":1030920100103,"costItem":101,"costCount":4500,"pondId":301020000},"5010094":{"id":5010094,"name":"buy_lure_shad01_4","mark":"","showStyle":3,"itemType":309,"goodsId":1030920100104,"costItem":101,"costCount":4500,"pondId":301020000},"5010095":{"id":5010095,"name":"buy_lure_shad01_5","mark":"","showStyle":3,"itemType":309,"goodsId":1030920100105,"costItem":101,"costCount":4500,"pondId":301020000},"5010096":{"id":5010096,"name":"buy_lure_shad01_6","mark":"","showStyle":3,"itemType":309,"goodsId":1030920100106,"costItem":101,"costCount":4500,"pondId":301020000},"5010097":{"id":5010097,"name":"buy_lure_shad01_7","mark":"","showStyle":3,"itemType":309,"goodsId":1030920100107,"costItem":101,"costCount":4500,"pondId":301020000},"5010098":{"id":5010098,"name":"buy_lure_grub01_1","mark":"","showStyle":3,"itemType":309,"goodsId":1030920200101,"costItem":101,"costCount":2500,"pondId":301020000},"5010099":{"id":5010099,"name":"buy_lure_grub01_2","mark":"","showStyle":3,"itemType":309,"goodsId":1030920200102,"costItem":101,"costCount":2500,"pondId":301020000},"5010100":{"id":5010100,"name":"buy_lure_grub01_3","mark":"","showStyle":3,"itemType":309,"goodsId":1030920200103,"costItem":101,"costCount":2500,"pondId":301020000},"5010101":{"id":5010101,"name":"buy_lure_grub01_4","mark":"","showStyle":3,"itemType":309,"goodsId":1030920200104,"costItem":101,"costCount":2500,"pondId":301020000},"5010102":{"id":5010102,"name":"buy_lure_grub01_5","mark":"","showStyle":3,"itemType":309,"goodsId":1030920200105,"costItem":101,"costCount":2500,"pondId":301020000},"5010103":{"id":5010103,"name":"buy_lure_grub01_6","mark":"","showStyle":3,"itemType":309,"goodsId":1030920200106,"costItem":101,"costCount":2500,"pondId":301020000},"5010104":{"id":5010104,"name":"buy_lure_grub01_7","mark":"","showStyle":3,"itemType":309,"goodsId":1030920200107,"costItem":101,"costCount":2500,"pondId":301020000},"5010105":{"id":5010105,"name":"buy_lure_popper01_1","mark":"","showStyle":3,"itemType":309,"goodsId":1030930200101,"costItem":101,"costCount":4000,"pondId":301020000},"5010106":{"id":5010106,"name":"buy_lure_popper01_2","mark":"","showStyle":3,"itemType":309,"goodsId":1030930200102,"costItem":101,"costCount":4000,"pondId":301020000},"5010107":{"id":5010107,"name":"buy_lure_popper01_3","mark":"","showStyle":3,"itemType":309,"goodsId":1030930200103,"costItem":101,"costCount":4000,"pondId":301020000},"5010108":{"id":5010108,"name":"buy_lure_popper01_4","mark":"","showStyle":3,"itemType":309,"goodsId":1030930200104,"costItem":101,"costCount":4000,"pondId":301020000},"5010109":{"id":5010109,"name":"buy_lure_popper01_5","mark":"","showStyle":3,"itemType":309,"goodsId":1030930200105,"costItem":101,"costCount":4000,"pondId":301020000},"5010110":{"id":5010110,"name":"buy_lure_popper01_6","mark":"","showStyle":3,"itemType":309,"goodsId":1030930200106,"costItem":101,"costCount":4000,"pondId":301020000},"5010111":{"id":5010111,"name":"buy_lure_popper01_7","mark":"","showStyle":3,"itemType":309,"goodsId":1030930200107,"costItem":101,"costCount":4000,"pondId":301020000},"5010112":{"id":5010112,"name":"buy_lure_popper02_1","mark":"","showStyle":3,"itemType":309,"goodsId":1030930200201,"costItem":101,"costCount":4000,"pondId":301020000},"5010113":{"id":5010113,"name":"buy_lure_popper02_2","mark":"","showStyle":3,"itemType":309,"goodsId":1030930200202,"costItem":101,"costCount":4000,"pondId":301020000},"5010114":{"id":5010114,"name":"buy_lure_popper02_3","mark":"","showStyle":3,"itemType":309,"goodsId":1030930200203,"costItem":101,"costCount":4000,"pondId":301020000},"5010115":{"id":5010115,"name":"buy_lure_popper02_4","mark":"","showStyle":3,"itemType":309,"goodsId":1030930200204,"costItem":101,"costCount":4000,"pondId":301020000},"5010116":{"id":5010116,"name":"buy_lure_popper02_5","mark":"","showStyle":3,"itemType":309,"goodsId":1030930200205,"costItem":101,"costCount":4000,"pondId":301020000},"5010117":{"id":5010117,"name":"buy_lure_popper02_6","mark":"","showStyle":3,"itemType":309,"goodsId":1030930200206,"costItem":101,"costCount":4000,"pondId":301020000},"5010118":{"id":5010118,"name":"buy_lure_popper02_7","mark":"","showStyle":3,"itemType":309,"goodsId":1030930200207,"costItem":101,"costCount":4000,"pondId":301020000},"5010119":{"id":5010119,"name":"buy_lure_minnow01_1","mark":"","showStyle":3,"itemType":309,"goodsId":1030930100101,"costItem":101,"costCount":2500,"pondId":301020000},"5010120":{"id":5010120,"name":"buy_lure_minnow01_2","mark":"","showStyle":3,"itemType":309,"goodsId":1030930100102,"costItem":101,"costCount":2500,"pondId":301020000},"5010121":{"id":5010121,"name":"buy_lure_minnow01_3","mark":"","showStyle":3,"itemType":309,"goodsId":1030930100103,"costItem":101,"costCount":2500,"pondId":301020000},"5010122":{"id":5010122,"name":"buy_lure_minnow01_4","mark":"","showStyle":3,"itemType":309,"goodsId":1030930100104,"costItem":101,"costCount":2500,"pondId":301020000},"5010123":{"id":5010123,"name":"buy_lure_minnow01_5","mark":"","showStyle":3,"itemType":309,"goodsId":1030930100105,"costItem":101,"costCount":2500,"pondId":301020000},"5010124":{"id":5010124,"name":"buy_lure_minnow01_6","mark":"","showStyle":3,"itemType":309,"goodsId":1030930100106,"costItem":101,"costCount":2500,"pondId":301020000},"5010125":{"id":5010125,"name":"buy_lure_minnow01_7","mark":"","showStyle":3,"itemType":309,"goodsId":1030930100107,"costItem":101,"costCount":2500,"pondId":301020000},"5010126":{"id":5010126,"name":"buy_lure_minnow02_1","mark":"","showStyle":3,"itemType":309,"goodsId":1030930100201,"costItem":101,"costCount":4000,"pondId":301020000},"5010127":{"id":5010127,"name":"buy_lure_minnow02_2","mark":"","showStyle":3,"itemType":309,"goodsId":1030930100202,"costItem":101,"costCount":4000,"pondId":301020000},"5010128":{"id":5010128,"name":"buy_lure_minnow02_3","mark":"","showStyle":3,"itemType":309,"goodsId":1030930100203,"costItem":101,"costCount":4000,"pondId":301020000},"5010129":{"id":5010129,"name":"buy_lure_minnow02_4","mark":"","showStyle":3,"itemType":309,"goodsId":1030930100204,"costItem":101,"costCount":4000,"pondId":301020000},"5010130":{"id":5010130,"name":"buy_lure_minnow02_5","mark":"","showStyle":3,"itemType":309,"goodsId":1030930100205,"costItem":101,"costCount":4000,"pondId":301020000},"5010131":{"id":5010131,"name":"buy_lure_minnow02_6","mark":"","showStyle":3,"itemType":309,"goodsId":1030930100206,"costItem":101,"costCount":4000,"pondId":301020000},"5010132":{"id":5010132,"name":"buy_lure_minnow02_7","mark":"","showStyle":3,"itemType":309,"goodsId":1030930100207,"costItem":101,"costCount":4000,"pondId":301020000},"5010133":{"id":5010133,"name":"buy_lure_spoon01_1","mark":"","showStyle":3,"itemType":309,"goodsId":1030930300101,"costItem":101,"costCount":500,"pondId":301020000},"5010134":{"id":5010134,"name":"buy_lure_spoon01_2","mark":"","showStyle":3,"itemType":309,"goodsId":1030930300102,"costItem":101,"costCount":500,"pondId":301020000},"5010135":{"id":5010135,"name":"buy_lure_spoon01_3","mark":"","showStyle":3,"itemType":309,"goodsId":1030930300103,"costItem":101,"costCount":500,"pondId":301020000},"5010136":{"id":5010136,"name":"buy_lure_spoon01_4","mark":"","showStyle":3,"itemType":309,"goodsId":1030930300104,"costItem":101,"costCount":500,"pondId":301020000},"5010137":{"id":5010137,"name":"buy_lure_spoon01_5","mark":"","showStyle":3,"itemType":309,"goodsId":1030930300105,"costItem":101,"costCount":500,"pondId":301020000},"5010138":{"id":5010138,"name":"buy_lure_spoon01_6","mark":"","showStyle":3,"itemType":309,"goodsId":1030930300106,"costItem":101,"costCount":500,"pondId":301020000},"5010139":{"id":5010139,"name":"buy_lure_spoon01_7","mark":"","showStyle":3,"itemType":309,"goodsId":1030930300107,"costItem":101,"costCount":500,"pondId":301020000},"5010140":{"id":5010140,"name":"buy_lure_spinner01_1","mark":"","showStyle":3,"itemType":309,"goodsId":1030930400101,"costItem":101,"costCount":2500,"pondId":301020000},"5010141":{"id":5010141,"name":"buy_lure_spinner01_2","mark":"","showStyle":3,"itemType":309,"goodsId":1030930400102,"costItem":101,"costCount":2500,"pondId":301020000},"5010142":{"id":5010142,"name":"buy_lure_spinner01_3","mark":"","showStyle":3,"itemType":309,"goodsId":1030930400103,"costItem":101,"costCount":2500,"pondId":301020000},"5010143":{"id":5010143,"name":"buy_lure_spinner01_4","mark":"","showStyle":3,"itemType":309,"goodsId":1030930400104,"costItem":101,"costCount":2500,"pondId":301020000},"5010144":{"id":5010144,"name":"buy_lure_spinner01_5","mark":"","showStyle":3,"itemType":309,"goodsId":1030930400105,"costItem":101,"costCount":2500,"pondId":301020000},"5010145":{"id":5010145,"name":"buy_lure_spinner01_6","mark":"","showStyle":3,"itemType":309,"goodsId":1030930400106,"costItem":101,"costCount":2500,"pondId":301020000},"5010146":{"id":5010146,"name":"buy_lure_spinner01_7","mark":"","showStyle":3,"itemType":309,"goodsId":1030930400107,"costItem":101,"costCount":2500,"pondId":301020000},"5010147":{"id":5010147,"name":"buy_lure_spinnerbait01_1","mark":"","showStyle":3,"itemType":309,"goodsId":1030931200101,"costItem":101,"costCount":4000,"pondId":301020000},"5010148":{"id":5010148,"name":"buy_lure_spinnerbait01_2","mark":"","showStyle":3,"itemType":309,"goodsId":1030931200102,"costItem":101,"costCount":4000,"pondId":301020000},"5010149":{"id":5010149,"name":"buy_lure_spinnerbait01_3","mark":"","showStyle":3,"itemType":309,"goodsId":1030931200103,"costItem":101,"costCount":4000,"pondId":301020000},"5010150":{"id":5010150,"name":"buy_lure_spinnerbait01_4","mark":"","showStyle":3,"itemType":309,"goodsId":1030931200104,"costItem":101,"costCount":4000,"pondId":301020000},"5010151":{"id":5010151,"name":"buy_lure_spinnerbait01_5","mark":"","showStyle":3,"itemType":309,"goodsId":1030931200105,"costItem":101,"costCount":4000,"pondId":301020000},"5010152":{"id":5010152,"name":"buy_lure_spinnerbait01_6","mark":"","showStyle":3,"itemType":309,"goodsId":1030931200106,"costItem":101,"costCount":4000,"pondId":301020000},"5010153":{"id":5010153,"name":"buy_lure_spinnerbait01_7","mark":"","showStyle":3,"itemType":309,"goodsId":1030931200107,"costItem":101,"costCount":4000,"pondId":301020000},"5010161":{"id":5010161,"name":"buy_lure_crayfish01_1","mark":"","showStyle":3,"itemType":309,"goodsId":1030920400301,"costItem":101,"costCount":4500,"pondId":301020000},"5010162":{"id":5010162,"name":"buy_lure_crayfish01_2","mark":"","showStyle":3,"itemType":309,"goodsId":1030920400302,"costItem":101,"costCount":4500,"pondId":301020000},"5010163":{"id":5010163,"name":"buy_lure_crayfish01_3","mark":"","showStyle":3,"itemType":309,"goodsId":1030920400303,"costItem":101,"costCount":4500,"pondId":301020000},"5010164":{"id":5010164,"name":"buy_lure_crayfish01_4","mark":"","showStyle":3,"itemType":309,"goodsId":1030920400304,"costItem":101,"costCount":4500,"pondId":301020000},"5010165":{"id":5010165,"name":"buy_lure_crayfish01_5","mark":"","showStyle":3,"itemType":309,"goodsId":1030920400305,"costItem":101,"costCount":4500,"pondId":301020000},"5010166":{"id":5010166,"name":"buy_lure_crayfish01_6","mark":"","showStyle":3,"itemType":309,"goodsId":1030920400306,"costItem":101,"costCount":4500,"pondId":301020000},"5010167":{"id":5010167,"name":"buy_lure_crayfish01_7","mark":"","showStyle":3,"itemType":309,"goodsId":1030920400307,"costItem":101,"costCount":4500,"pondId":301020000},"5010168":{"id":5010168,"name":"buy_lure_worm01_1","mark":"","showStyle":3,"itemType":309,"goodsId":1030920300101,"costItem":101,"costCount":2500,"pondId":301020000},"5010169":{"id":5010169,"name":"buy_lure_worm01_2","mark":"","showStyle":3,"itemType":309,"goodsId":1030920300102,"costItem":101,"costCount":2500,"pondId":301020000},"5010170":{"id":5010170,"name":"buy_lure_worm01_3","mark":"","showStyle":3,"itemType":309,"goodsId":1030920300103,"costItem":101,"costCount":2500,"pondId":301020000},"5010171":{"id":5010171,"name":"buy_lure_worm01_4","mark":"","showStyle":3,"itemType":309,"goodsId":1030920300104,"costItem":101,"costCount":2500,"pondId":301020000},"5010172":{"id":5010172,"name":"buy_lure_worm01_5","mark":"","showStyle":3,"itemType":309,"goodsId":1030920300105,"costItem":101,"costCount":2500,"pondId":301020000},"5010173":{"id":5010173,"name":"buy_lure_worm01_6","mark":"","showStyle":3,"itemType":309,"goodsId":1030920300106,"costItem":101,"costCount":2500,"pondId":301020000},"5010174":{"id":5010174,"name":"buy_lure_worm01_7","mark":"","showStyle":3,"itemType":309,"goodsId":1030920300107,"costItem":101,"costCount":2500,"pondId":301020000},"5010329":{"id":5010329,"name":"buy_lure_frog01_1","mark":"","showStyle":3,"itemType":309,"goodsId":1030931000101,"costItem":101,"costCount":1000,"pondId":301020000},"5010330":{"id":5010330,"name":"buy_lure_frog01_2","mark":"","showStyle":3,"itemType":309,"goodsId":1030931000102,"costItem":101,"costCount":1000,"pondId":301020000},"5010331":{"id":5010331,"name":"buy_lure_frog01_3","mark":"","showStyle":3,"itemType":309,"goodsId":1030931000103,"costItem":101,"costCount":1000,"pondId":301020000},"5010332":{"id":5010332,"name":"buy_lure_frog01_4","mark":"","showStyle":3,"itemType":309,"goodsId":1030931000104,"costItem":101,"costCount":1000,"pondId":301020000},"5010333":{"id":5010333,"name":"buy_lure_frog01_5","mark":"","showStyle":3,"itemType":309,"goodsId":1030931000105,"costItem":101,"costCount":1000,"pondId":301020000},"5010334":{"id":5010334,"name":"buy_lure_frog01_6","mark":"","showStyle":3,"itemType":309,"goodsId":1030931000106,"costItem":101,"costCount":1000,"pondId":301020000},"5010335":{"id":5010335,"name":"buy_lure_frog01_7","mark":"","showStyle":3,"itemType":309,"goodsId":1030931000107,"costItem":101,"costCount":1000,"pondId":301020000},"5010357":{"id":5010357,"name":"buy_hook_sleeve_black01_1","mark":"","showStyle":3,"itemType":308,"goodsId":1030810200101,"costItem":101,"costCount":250,"pondId":301020000},"5010358":{"id":5010358,"name":"buy_hook_sleeve_black01_2","mark":"","showStyle":3,"itemType":308,"goodsId":1030810200102,"costItem":101,"costCount":280,"pondId":301020000},"5010359":{"id":5010359,"name":"buy_hook_sleeve_black01_3","mark":"","showStyle":3,"itemType":308,"goodsId":1030810200103,"costItem":101,"costCount":320,"pondId":301020000},"5010360":{"id":5010360,"name":"buy_hook_sleeve_black01_4","mark":"","showStyle":3,"itemType":308,"goodsId":1030810200104,"costItem":101,"costCount":360,"pondId":301020000},"5010361":{"id":5010361,"name":"buy_hook_sleeve_black01_5","mark":"","showStyle":3,"itemType":308,"goodsId":1030810200105,"costItem":101,"costCount":450,"pondId":301020000},"5010362":{"id":5010362,"name":"buy_hook_sleeve_black01_6","mark":"","showStyle":3,"itemType":308,"goodsId":1030810200106,"costItem":101,"costCount":520,"pondId":301020000},"5010363":{"id":5010363,"name":"buy_hook_sleeve_black01_7","mark":"","showStyle":3,"itemType":308,"goodsId":1030810200107,"costItem":101,"costCount":560,"pondId":301020000},"5010364":{"id":5010364,"name":"buy_hook_sleeve_black01_8","mark":"","showStyle":3,"itemType":308,"goodsId":1030810200108,"costItem":101,"costCount":580,"pondId":301020000},"5010365":{"id":5010365,"name":"buy_hook_fisheye01_1","mark":"","showStyle":3,"itemType":308,"goodsId":1030820200101,"costItem":101,"costCount":1900,"pondId":301020000},"5010366":{"id":5010366,"name":"buy_hook_fisheye01_2","mark":"","showStyle":3,"itemType":308,"goodsId":1030820200102,"costItem":101,"costCount":1950,"pondId":301020000},"5010367":{"id":5010367,"name":"buy_hook_fisheye01_3","mark":"","showStyle":3,"itemType":308,"goodsId":1030820200103,"costItem":101,"costCount":1980,"pondId":301020000},"5010368":{"id":5010368,"name":"buy_hook_fisheye01_4","mark":"","showStyle":3,"itemType":308,"goodsId":1030820200104,"costItem":101,"costCount":2060,"pondId":301020000},"5010369":{"id":5010369,"name":"buy_hook_fisheye01_5","mark":"","showStyle":3,"itemType":308,"goodsId":1030820200105,"costItem":101,"costCount":2080,"pondId":301020000},"5010370":{"id":5010370,"name":"buy_hook_fisheye01_6","mark":"","showStyle":3,"itemType":308,"goodsId":1030820200106,"costItem":101,"costCount":2090,"pondId":301020000},"5010371":{"id":5010371,"name":"buy_hook_fisheye01_7","mark":"","showStyle":3,"itemType":308,"goodsId":1030820200107,"costItem":101,"costCount":2100,"pondId":301020000},"5010372":{"id":5010372,"name":"buy_hook_fisheye01_8","mark":"","showStyle":3,"itemType":308,"goodsId":1030820200108,"costItem":101,"costCount":2150,"pondId":301020000},"5010373":{"id":5010373,"name":"buy_hook_head01_1","mark":"","showStyle":3,"itemType":308,"goodsId":1030820100101,"costItem":101,"costCount":1420,"pondId":301020000},"5010374":{"id":5010374,"name":"buy_hook_head01_2","mark":"","showStyle":3,"itemType":308,"goodsId":1030820100102,"costItem":101,"costCount":1440,"pondId":301020000},"5010375":{"id":5010375,"name":"buy_hook_head01_3","mark":"","showStyle":3,"itemType":308,"goodsId":1030820100103,"costItem":101,"costCount":1480,"pondId":301020000},"5010376":{"id":5010376,"name":"buy_hook_head01_4","mark":"","showStyle":3,"itemType":308,"goodsId":1030820100104,"costItem":101,"costCount":1520,"pondId":301020000},"5010377":{"id":5010377,"name":"buy_hook_head01_5","mark":"","showStyle":3,"itemType":308,"goodsId":1030820100105,"costItem":101,"costCount":1530,"pondId":301020000},"5010378":{"id":5010378,"name":"buy_hook_head01_6","mark":"","showStyle":3,"itemType":308,"goodsId":1030820100106,"costItem":101,"costCount":1560,"pondId":301020000},"5010379":{"id":5010379,"name":"buy_hook_head01_7","mark":"","showStyle":3,"itemType":308,"goodsId":1030820100107,"costItem":101,"costCount":1580,"pondId":301020000},"5010380":{"id":5010380,"name":"buy_hook_wacky01_1","mark":"","showStyle":3,"itemType":308,"goodsId":1030820400101,"costItem":101,"costCount":1750,"pondId":301020000},"5010381":{"id":5010381,"name":"buy_hook_wacky01_2","mark":"","showStyle":3,"itemType":308,"goodsId":1030820400102,"costItem":101,"costCount":1780,"pondId":301020000},"5010382":{"id":5010382,"name":"buy_hook_wacky01_3","mark":"","showStyle":3,"itemType":308,"goodsId":1030820400103,"costItem":101,"costCount":1790,"pondId":301020000},"5010383":{"id":5010383,"name":"buy_hook_wacky01_4","mark":"","showStyle":3,"itemType":308,"goodsId":1030820400104,"costItem":101,"costCount":1820,"pondId":301020000},"5010384":{"id":5010384,"name":"buy_hook_wacky01_5","mark":"","showStyle":3,"itemType":308,"goodsId":1030820400105,"costItem":101,"costCount":1840,"pondId":301020000},"5010385":{"id":5010385,"name":"buy_hook_wacky01_6","mark":"","showStyle":3,"itemType":308,"goodsId":1030820400106,"costItem":101,"costCount":1880,"pondId":301020000},"5010386":{"id":5010386,"name":"buy_hook_wacky01_7","mark":"","showStyle":3,"itemType":308,"goodsId":1030820400107,"costItem":101,"costCount":1900,"pondId":301020000},"5010387":{"id":5010387,"name":"buy_hook_offset01_1","mark":"","showStyle":3,"itemType":308,"goodsId":1030820300101,"costItem":101,"costCount":880,"pondId":301020000},"5010388":{"id":5010388,"name":"buy_hook_offset01_2","mark":"","showStyle":3,"itemType":308,"goodsId":1030820300102,"costItem":101,"costCount":940,"pondId":301020000},"5010389":{"id":5010389,"name":"buy_hook_offset01_3","mark":"","showStyle":3,"itemType":308,"goodsId":1030820300103,"costItem":101,"costCount":980,"pondId":301020000},"5010390":{"id":5010390,"name":"buy_hook_offset01_4","mark":"","showStyle":3,"itemType":308,"goodsId":1030820300104,"costItem":101,"costCount":1040,"pondId":301020000},"5010391":{"id":5010391,"name":"buy_hook_offset01_5","mark":"","showStyle":3,"itemType":308,"goodsId":1030820300105,"costItem":101,"costCount":1060,"pondId":301020000},"5010392":{"id":5010392,"name":"buy_hook_offset01_6","mark":"","showStyle":3,"itemType":308,"goodsId":1030820300106,"costItem":101,"costCount":1080,"pondId":301020000},"5010393":{"id":5010393,"name":"buy_hook_offset01_7","mark":"","showStyle":3,"itemType":308,"goodsId":1030820300107,"costItem":101,"costCount":1100,"pondId":301020000},"5010415":{"id":5010415,"name":"buy_hook_sleeve_gold01_1","mark":"","showStyle":3,"itemType":308,"goodsId":1030810200201,"costItem":101,"costCount":2860,"pondId":301020000},"5010416":{"id":5010416,"name":"buy_hook_sleeve_gold01_2","mark":"","showStyle":3,"itemType":308,"goodsId":1030810200202,"costItem":101,"costCount":2880,"pondId":301020000},"5010417":{"id":5010417,"name":"buy_hook_sleeve_gold01_3","mark":"","showStyle":3,"itemType":308,"goodsId":1030810200203,"costItem":101,"costCount":2920,"pondId":301020000},"5010418":{"id":5010418,"name":"buy_hook_sleeve_gold01_4","mark":"","showStyle":3,"itemType":308,"goodsId":1030810200204,"costItem":101,"costCount":2960,"pondId":301020000},"5010419":{"id":5010419,"name":"buy_hook_sleeve_gold01_5","mark":"","showStyle":3,"itemType":308,"goodsId":1030810200205,"costItem":101,"costCount":2980,"pondId":301020000},"5010420":{"id":5010420,"name":"buy_hook_sleeve_gold01_6","mark":"","showStyle":3,"itemType":308,"goodsId":1030810200206,"costItem":101,"costCount":3050,"pondId":301020000},"5010421":{"id":5010421,"name":"buy_hook_sleeve_gold01_7","mark":"","showStyle":3,"itemType":308,"goodsId":1030810200207,"costItem":101,"costCount":3080,"pondId":301020000},"5010422":{"id":5010422,"name":"buy_hook_sleeve_red01_1","mark":"","showStyle":3,"itemType":308,"goodsId":1030810200301,"costItem":101,"costCount":1420,"pondId":301020000},"5010423":{"id":5010423,"name":"buy_hook_sleeve_red01_2","mark":"","showStyle":3,"itemType":308,"goodsId":1030810200302,"costItem":101,"costCount":1440,"pondId":301020000},"5010424":{"id":5010424,"name":"buy_hook_sleeve_red01_3","mark":"","showStyle":3,"itemType":308,"goodsId":1030810200303,"costItem":101,"costCount":1480,"pondId":301020000},"5010425":{"id":5010425,"name":"buy_hook_sleeve_red01_4","mark":"","showStyle":3,"itemType":308,"goodsId":1030810200304,"costItem":101,"costCount":1520,"pondId":301020000},"5010426":{"id":5010426,"name":"buy_hook_sleeve_red01_5","mark":"","showStyle":3,"itemType":308,"goodsId":1030810200305,"costItem":101,"costCount":1530,"pondId":301020000},"5010427":{"id":5010427,"name":"buy_hook_sleeve_red01_6","mark":"","showStyle":3,"itemType":308,"goodsId":1030810200306,"costItem":101,"costCount":1560,"pondId":301020000},"5010428":{"id":5010428,"name":"buy_hook_sleeve_red01_7","mark":"","showStyle":3,"itemType":308,"goodsId":1030810200307,"costItem":101,"costCount":1580,"pondId":301020000},"5010429":{"id":5010429,"name":"buy_hook_sleeve_silver01_1","mark":"","showStyle":3,"itemType":308,"goodsId":1030810200401,"costItem":101,"costCount":2420,"pondId":301020000},"5010430":{"id":5010430,"name":"buy_hook_sleeve_silver01_2","mark":"","showStyle":3,"itemType":308,"goodsId":1030810200402,"costItem":101,"costCount":2450,"pondId":301020000},"5010431":{"id":5010431,"name":"buy_hook_sleeve_silver01_3","mark":"","showStyle":3,"itemType":308,"goodsId":1030810200403,"costItem":101,"costCount":2500,"pondId":301020000},"5010432":{"id":5010432,"name":"buy_hook_sleeve_silver01_4","mark":"","showStyle":3,"itemType":308,"goodsId":1030810200404,"costItem":101,"costCount":2580,"pondId":301020000},"5010433":{"id":5010433,"name":"buy_hook_sleeve_silver01_5","mark":"","showStyle":3,"itemType":308,"goodsId":1030810200405,"costItem":101,"costCount":2600,"pondId":301020000},"5010434":{"id":5010434,"name":"buy_hook_sleeve_silver01_6","mark":"","showStyle":3,"itemType":308,"goodsId":1030810200406,"costItem":101,"costCount":2640,"pondId":301020000},"5010435":{"id":5010435,"name":"buy_hook_sleeve_silver01_7","mark":"","showStyle":3,"itemType":308,"goodsId":1030810200407,"costItem":101,"costCount":2660,"pondId":301020000},"5010436":{"id":5010436,"name":"buy_bait_mayfly","mark":"","showStyle":3,"itemType":305,"goodsId":1030510400101,"costItem":101,"costCount":8,"pondId":301020001},"5010437":{"id":5010437,"name":"buy_bait_fly","mark":"","showStyle":3,"itemType":305,"goodsId":1030510400201,"costItem":101,"costCount":10,"pondId":301020001},"5010438":{"id":5010438,"name":"buy_bait_bloodworm","mark":"","showStyle":3,"itemType":305,"goodsId":1030510400301,"costItem":101,"costCount":128,"pondId":301020001},"5010439":{"id":5010439,"name":"buy_bait_earthworm","mark":"","showStyle":3,"itemType":305,"goodsId":1030510400401,"costItem":101,"costCount":64,"pondId":301020001},"5010440":{"id":5010440,"name":"buy_bait_grasshopper","mark":"","showStyle":3,"itemType":305,"goodsId":1030510400501,"costItem":101,"costCount":8,"pondId":301020001},"5010441":{"id":5010441,"name":"buy_bait_minnow_1","mark":"","showStyle":3,"itemType":305,"goodsId":1030510600101,"costItem":101,"costCount":86,"pondId":301020001},"5010442":{"id":5010442,"name":"buy_bait_minnow_2","mark":"","showStyle":3,"itemType":305,"goodsId":1030510600102,"costItem":101,"costCount":88,"pondId":301020001},"5010443":{"id":5010443,"name":"buy_bait_minnow_3","mark":"","showStyle":3,"itemType":305,"goodsId":1030510600103,"costItem":101,"costCount":98,"pondId":301020001},"5010444":{"id":5010444,"name":"buy_bait_fish_cube_1","mark":"","showStyle":3,"itemType":305,"goodsId":1030511100101,"costItem":101,"costCount":16,"pondId":301020001},"5010445":{"id":5010445,"name":"buy_bait_fish_cube_2","mark":"","showStyle":3,"itemType":305,"goodsId":1030511100102,"costItem":101,"costCount":16,"pondId":301020001},"5010446":{"id":5010446,"name":"buy_bait_fish_cube_3","mark":"","showStyle":3,"itemType":305,"goodsId":1030511100103,"costItem":101,"costCount":16,"pondId":301020001},"5010447":{"id":5010447,"name":"buy_bait_salmon_roe","mark":"","showStyle":3,"itemType":305,"goodsId":1030511800101,"costItem":101,"costCount":200,"pondId":301020001},"5010448":{"id":5010448,"name":"buy_bait_shrimp","mark":"","showStyle":3,"itemType":305,"goodsId":1030510500101,"costItem":101,"costCount":428,"pondId":301020001},"5010449":{"id":5010449,"name":"buy_bait_crayfish","mark":"","showStyle":3,"itemType":305,"goodsId":1030510500201,"costItem":101,"costCount":250,"pondId":301020001},"5010450":{"id":5010450,"name":"buy_bait_clam_meat","mark":"","showStyle":3,"itemType":305,"goodsId":1030510500301,"costItem":101,"costCount":280,"pondId":301020001},"5010451":{"id":5010451,"name":"buy_bait_crayfish_tail_1","mark":"","showStyle":3,"itemType":305,"goodsId":1030511100201,"costItem":101,"costCount":150,"pondId":301020001},"5010452":{"id":5010452,"name":"buy_bait_crayfish_tail_2","mark":"","showStyle":3,"itemType":305,"goodsId":1030511100202,"costItem":101,"costCount":150,"pondId":301020001},"5010453":{"id":5010453,"name":"buy_bait_crayfish_tail_3","mark":"","showStyle":3,"itemType":305,"goodsId":1030511100203,"costItem":101,"costCount":150,"pondId":301020001},"5010454":{"id":5010454,"name":"buy_bait_meat_chunk_1","mark":"","showStyle":3,"itemType":305,"goodsId":1030511100301,"costItem":101,"costCount":350,"pondId":301020001},"5010455":{"id":5010455,"name":"buy_bait_meat_chunk_2","mark":"","showStyle":3,"itemType":305,"goodsId":1030511100302,"costItem":101,"costCount":350,"pondId":301020001},"5010456":{"id":5010456,"name":"buy_bait_meat_chunk_3","mark":"","showStyle":3,"itemType":305,"goodsId":1030511100303,"costItem":101,"costCount":350,"pondId":301020001},"5010457":{"id":5010457,"name":"buy_bait_honey_dough_1","mark":"","showStyle":3,"itemType":305,"goodsId":1030510900101,"costItem":101,"costCount":16,"pondId":301020001},"5010458":{"id":5010458,"name":"buy_bait_honey_dough_2","mark":"","showStyle":3,"itemType":305,"goodsId":1030510900102,"costItem":101,"costCount":16,"pondId":301020001},"5010459":{"id":5010459,"name":"buy_bait_honey_dough_3","mark":"","showStyle":3,"itemType":305,"goodsId":1030510900103,"costItem":101,"costCount":16,"pondId":301020001},"5010460":{"id":5010460,"name":"buy_bait_bread_1","mark":"","showStyle":3,"itemType":305,"goodsId":1030510900201,"costItem":101,"costCount":16,"pondId":301020001},"5010461":{"id":5010461,"name":"buy_bait_bread_2","mark":"","showStyle":3,"itemType":305,"goodsId":1030510900202,"costItem":101,"costCount":16,"pondId":301020001},"5010462":{"id":5010462,"name":"buy_bait_bread_3","mark":"","showStyle":3,"itemType":305,"goodsId":1030510900203,"costItem":101,"costCount":16,"pondId":301020001},"5010463":{"id":5010463,"name":"buy_bait_toast_1","mark":"","showStyle":3,"itemType":305,"goodsId":1030510900301,"costItem":101,"costCount":8,"pondId":301020001},"5010464":{"id":5010464,"name":"buy_bait_toast_2","mark":"","showStyle":3,"itemType":305,"goodsId":1030510900302,"costItem":101,"costCount":8,"pondId":301020001},"5010465":{"id":5010465,"name":"buy_bait_toast_3","mark":"","showStyle":3,"itemType":305,"goodsId":1030510900303,"costItem":101,"costCount":8,"pondId":301020001},"5010466":{"id":5010466,"name":"buy_bait_seeds","mark":"","showStyle":3,"itemType":305,"goodsId":1030510300101,"costItem":101,"costCount":150,"pondId":301020001},"5010467":{"id":5010467,"name":"buy_bait_niblet","mark":"","showStyle":3,"itemType":305,"goodsId":1030511000201,"costItem":101,"costCount":64,"pondId":301020001},"5010468":{"id":5010468,"name":"buy_bait_cheese_1","mark":"","showStyle":3,"itemType":305,"goodsId":1030511200101,"costItem":101,"costCount":200,"pondId":301020001},"5010469":{"id":5010469,"name":"buy_bait_cheese_2","mark":"","showStyle":3,"itemType":305,"goodsId":1030511200102,"costItem":101,"costCount":250,"pondId":301020001},"5010470":{"id":5010470,"name":"buy_bait_cheese_3","mark":"","showStyle":3,"itemType":305,"goodsId":1030511200103,"costItem":101,"costCount":280,"pondId":301020001},"5010471":{"id":5010471,"name":"buy_lure_shad01_1","mark":"","showStyle":3,"itemType":309,"goodsId":1030920100101,"costItem":101,"costCount":4500,"pondId":301020001},"5010472":{"id":5010472,"name":"buy_lure_shad01_2","mark":"","showStyle":3,"itemType":309,"goodsId":1030920100102,"costItem":101,"costCount":4500,"pondId":301020001},"5010473":{"id":5010473,"name":"buy_lure_shad01_3","mark":"","showStyle":3,"itemType":309,"goodsId":1030920100103,"costItem":101,"costCount":4500,"pondId":301020001},"5010474":{"id":5010474,"name":"buy_lure_shad01_4","mark":"","showStyle":3,"itemType":309,"goodsId":1030920100104,"costItem":101,"costCount":4500,"pondId":301020001},"5010475":{"id":5010475,"name":"buy_lure_shad01_5","mark":"","showStyle":3,"itemType":309,"goodsId":1030920100105,"costItem":101,"costCount":4500,"pondId":301020001},"5010476":{"id":5010476,"name":"buy_lure_shad01_6","mark":"","showStyle":3,"itemType":309,"goodsId":1030920100106,"costItem":101,"costCount":4500,"pondId":301020001},"5010477":{"id":5010477,"name":"buy_lure_shad01_7","mark":"","showStyle":3,"itemType":309,"goodsId":1030920100107,"costItem":101,"costCount":4500,"pondId":301020001},"5010478":{"id":5010478,"name":"buy_lure_grub01_1","mark":"","showStyle":3,"itemType":309,"goodsId":1030920200101,"costItem":101,"costCount":2500,"pondId":301020001},"5010479":{"id":5010479,"name":"buy_lure_grub01_2","mark":"","showStyle":3,"itemType":309,"goodsId":1030920200102,"costItem":101,"costCount":2500,"pondId":301020001},"5010480":{"id":5010480,"name":"buy_lure_grub01_3","mark":"","showStyle":3,"itemType":309,"goodsId":1030920200103,"costItem":101,"costCount":2500,"pondId":301020001},"5010481":{"id":5010481,"name":"buy_lure_grub01_4","mark":"","showStyle":3,"itemType":309,"goodsId":1030920200104,"costItem":101,"costCount":2500,"pondId":301020001},"5010482":{"id":5010482,"name":"buy_lure_grub01_5","mark":"","showStyle":3,"itemType":309,"goodsId":1030920200105,"costItem":101,"costCount":2500,"pondId":301020001},"5010483":{"id":5010483,"name":"buy_lure_grub01_6","mark":"","showStyle":3,"itemType":309,"goodsId":1030920200106,"costItem":101,"costCount":2500,"pondId":301020001},"5010484":{"id":5010484,"name":"buy_lure_grub01_7","mark":"","showStyle":3,"itemType":309,"goodsId":1030920200107,"costItem":101,"costCount":2500,"pondId":301020001},"5010485":{"id":5010485,"name":"buy_lure_popper01_1","mark":"","showStyle":3,"itemType":309,"goodsId":1030930200101,"costItem":101,"costCount":4000,"pondId":301020001},"5010486":{"id":5010486,"name":"buy_lure_popper01_2","mark":"","showStyle":3,"itemType":309,"goodsId":1030930200102,"costItem":101,"costCount":4000,"pondId":301020001},"5010487":{"id":5010487,"name":"buy_lure_popper01_3","mark":"","showStyle":3,"itemType":309,"goodsId":1030930200103,"costItem":101,"costCount":4000,"pondId":301020001},"5010488":{"id":5010488,"name":"buy_lure_popper01_4","mark":"","showStyle":3,"itemType":309,"goodsId":1030930200104,"costItem":101,"costCount":4000,"pondId":301020001},"5010489":{"id":5010489,"name":"buy_lure_popper01_5","mark":"","showStyle":3,"itemType":309,"goodsId":1030930200105,"costItem":101,"costCount":4000,"pondId":301020001},"5010490":{"id":5010490,"name":"buy_lure_popper01_6","mark":"","showStyle":3,"itemType":309,"goodsId":1030930200106,"costItem":101,"costCount":4000,"pondId":301020001},"5010491":{"id":5010491,"name":"buy_lure_popper01_7","mark":"","showStyle":3,"itemType":309,"goodsId":1030930200107,"costItem":101,"costCount":4000,"pondId":301020001},"5010492":{"id":5010492,"name":"buy_lure_popper02_1","mark":"","showStyle":3,"itemType":309,"goodsId":1030930200201,"costItem":101,"costCount":4000,"pondId":301020001},"5010493":{"id":5010493,"name":"buy_lure_popper02_2","mark":"","showStyle":3,"itemType":309,"goodsId":1030930200202,"costItem":101,"costCount":4000,"pondId":301020001},"5010494":{"id":5010494,"name":"buy_lure_popper02_3","mark":"","showStyle":3,"itemType":309,"goodsId":1030930200203,"costItem":101,"costCount":4000,"pondId":301020001},"5010495":{"id":5010495,"name":"buy_lure_popper02_4","mark":"","showStyle":3,"itemType":309,"goodsId":1030930200204,"costItem":101,"costCount":4000,"pondId":301020001},"5010496":{"id":5010496,"name":"buy_lure_popper02_5","mark":"","showStyle":3,"itemType":309,"goodsId":1030930200205,"costItem":101,"costCount":4000,"pondId":301020001},"5010497":{"id":5010497,"name":"buy_lure_popper02_6","mark":"","showStyle":3,"itemType":309,"goodsId":1030930200206,"costItem":101,"costCount":4000,"pondId":301020001},"5010498":{"id":5010498,"name":"buy_lure_popper02_7","mark":"","showStyle":3,"itemType":309,"goodsId":1030930200207,"costItem":101,"costCount":4000,"pondId":301020001},"5010499":{"id":5010499,"name":"buy_lure_minnow01_1","mark":"","showStyle":3,"itemType":309,"goodsId":1030930100101,"costItem":101,"costCount":2500,"pondId":301020001},"5010500":{"id":5010500,"name":"buy_lure_minnow01_2","mark":"","showStyle":3,"itemType":309,"goodsId":1030930100102,"costItem":101,"costCount":2500,"pondId":301020001},"5010501":{"id":5010501,"name":"buy_lure_minnow01_3","mark":"","showStyle":3,"itemType":309,"goodsId":1030930100103,"costItem":101,"costCount":2500,"pondId":301020001},"5010502":{"id":5010502,"name":"buy_lure_minnow01_4","mark":"","showStyle":3,"itemType":309,"goodsId":1030930100104,"costItem":101,"costCount":2500,"pondId":301020001},"5010503":{"id":5010503,"name":"buy_lure_minnow01_5","mark":"","showStyle":3,"itemType":309,"goodsId":1030930100105,"costItem":101,"costCount":2500,"pondId":301020001},"5010504":{"id":5010504,"name":"buy_lure_minnow01_6","mark":"","showStyle":3,"itemType":309,"goodsId":1030930100106,"costItem":101,"costCount":2500,"pondId":301020001},"5010505":{"id":5010505,"name":"buy_lure_minnow01_7","mark":"","showStyle":3,"itemType":309,"goodsId":1030930100107,"costItem":101,"costCount":2500,"pondId":301020001},"5010506":{"id":5010506,"name":"buy_lure_minnow02_1","mark":"","showStyle":3,"itemType":309,"goodsId":1030930100201,"costItem":101,"costCount":4000,"pondId":301020001},"5010507":{"id":5010507,"name":"buy_lure_minnow02_2","mark":"","showStyle":3,"itemType":309,"goodsId":1030930100202,"costItem":101,"costCount":4000,"pondId":301020001},"5010508":{"id":5010508,"name":"buy_lure_minnow02_3","mark":"","showStyle":3,"itemType":309,"goodsId":1030930100203,"costItem":101,"costCount":4000,"pondId":301020001},"5010509":{"id":5010509,"name":"buy_lure_minnow02_4","mark":"","showStyle":3,"itemType":309,"goodsId":1030930100204,"costItem":101,"costCount":4000,"pondId":301020001},"5010510":{"id":5010510,"name":"buy_lure_minnow02_5","mark":"","showStyle":3,"itemType":309,"goodsId":1030930100205,"costItem":101,"costCount":4000,"pondId":301020001},"5010511":{"id":5010511,"name":"buy_lure_minnow02_6","mark":"","showStyle":3,"itemType":309,"goodsId":1030930100206,"costItem":101,"costCount":4000,"pondId":301020001},"5010512":{"id":5010512,"name":"buy_lure_minnow02_7","mark":"","showStyle":3,"itemType":309,"goodsId":1030930100207,"costItem":101,"costCount":4000,"pondId":301020001},"5010513":{"id":5010513,"name":"buy_lure_spoon01_1","mark":"","showStyle":3,"itemType":309,"goodsId":1030930300101,"costItem":101,"costCount":500,"pondId":301020001},"5010514":{"id":5010514,"name":"buy_lure_spoon01_2","mark":"","showStyle":3,"itemType":309,"goodsId":1030930300102,"costItem":101,"costCount":500,"pondId":301020001},"5010515":{"id":5010515,"name":"buy_lure_spoon01_3","mark":"","showStyle":3,"itemType":309,"goodsId":1030930300103,"costItem":101,"costCount":500,"pondId":301020001},"5010516":{"id":5010516,"name":"buy_lure_spoon01_4","mark":"","showStyle":3,"itemType":309,"goodsId":1030930300104,"costItem":101,"costCount":500,"pondId":301020001},"5010517":{"id":5010517,"name":"buy_lure_spoon01_5","mark":"","showStyle":3,"itemType":309,"goodsId":1030930300105,"costItem":101,"costCount":500,"pondId":301020001},"5010518":{"id":5010518,"name":"buy_lure_spoon01_6","mark":"","showStyle":3,"itemType":309,"goodsId":1030930300106,"costItem":101,"costCount":500,"pondId":301020001},"5010519":{"id":5010519,"name":"buy_lure_spoon01_7","mark":"","showStyle":3,"itemType":309,"goodsId":1030930300107,"costItem":101,"costCount":500,"pondId":301020001},"5010520":{"id":5010520,"name":"buy_lure_spinner01_1","mark":"","showStyle":3,"itemType":309,"goodsId":1030930400101,"costItem":101,"costCount":2500,"pondId":301020001},"5010521":{"id":5010521,"name":"buy_lure_spinner01_2","mark":"","showStyle":3,"itemType":309,"goodsId":1030930400102,"costItem":101,"costCount":2500,"pondId":301020001},"5010522":{"id":5010522,"name":"buy_lure_spinner01_3","mark":"","showStyle":3,"itemType":309,"goodsId":1030930400103,"costItem":101,"costCount":2500,"pondId":301020001},"5010523":{"id":5010523,"name":"buy_lure_spinner01_4","mark":"","showStyle":3,"itemType":309,"goodsId":1030930400104,"costItem":101,"costCount":2500,"pondId":301020001},"5010524":{"id":5010524,"name":"buy_lure_spinner01_5","mark":"","showStyle":3,"itemType":309,"goodsId":1030930400105,"costItem":101,"costCount":2500,"pondId":301020001},"5010525":{"id":5010525,"name":"buy_lure_spinner01_6","mark":"","showStyle":3,"itemType":309,"goodsId":1030930400106,"costItem":101,"costCount":2500,"pondId":301020001},"5010526":{"id":5010526,"name":"buy_lure_spinner01_7","mark":"","showStyle":3,"itemType":309,"goodsId":1030930400107,"costItem":101,"costCount":2500,"pondId":301020001},"5010527":{"id":5010527,"name":"buy_lure_spinnerbait01_1","mark":"","showStyle":3,"itemType":309,"goodsId":1030931200101,"costItem":101,"costCount":4000,"pondId":301020001},"5010528":{"id":5010528,"name":"buy_lure_spinnerbait01_2","mark":"","showStyle":3,"itemType":309,"goodsId":1030931200102,"costItem":101,"costCount":4000,"pondId":301020001},"5010529":{"id":5010529,"name":"buy_lure_spinnerbait01_3","mark":"","showStyle":3,"itemType":309,"goodsId":1030931200103,"costItem":101,"costCount":4000,"pondId":301020001},"5010530":{"id":5010530,"name":"buy_lure_spinnerbait01_4","mark":"","showStyle":3,"itemType":309,"goodsId":1030931200104,"costItem":101,"costCount":4000,"pondId":301020001},"5010531":{"id":5010531,"name":"buy_lure_spinnerbait01_5","mark":"","showStyle":3,"itemType":309,"goodsId":1030931200105,"costItem":101,"costCount":4000,"pondId":301020001},"5010532":{"id":5010532,"name":"buy_lure_spinnerbait01_6","mark":"","showStyle":3,"itemType":309,"goodsId":1030931200106,"costItem":101,"costCount":4000,"pondId":301020001},"5010533":{"id":5010533,"name":"buy_lure_spinnerbait01_7","mark":"","showStyle":3,"itemType":309,"goodsId":1030931200107,"costItem":101,"costCount":4000,"pondId":301020001},"5010541":{"id":5010541,"name":"buy_lure_crayfish01_1","mark":"","showStyle":3,"itemType":309,"goodsId":1030920400301,"costItem":101,"costCount":3000,"pondId":301020001},"5010542":{"id":5010542,"name":"buy_lure_crayfish01_2","mark":"","showStyle":3,"itemType":309,"goodsId":1030920400302,"costItem":101,"costCount":3000,"pondId":301020001},"5010543":{"id":5010543,"name":"buy_lure_crayfish01_3","mark":"","showStyle":3,"itemType":309,"goodsId":1030920400303,"costItem":101,"costCount":3000,"pondId":301020001},"5010544":{"id":5010544,"name":"buy_lure_crayfish01_4","mark":"","showStyle":3,"itemType":309,"goodsId":1030920400304,"costItem":101,"costCount":3000,"pondId":301020001},"5010545":{"id":5010545,"name":"buy_lure_crayfish01_5","mark":"","showStyle":3,"itemType":309,"goodsId":1030920400305,"costItem":101,"costCount":3000,"pondId":301020001},"5010546":{"id":5010546,"name":"buy_lure_crayfish01_6","mark":"","showStyle":3,"itemType":309,"goodsId":1030920400306,"costItem":101,"costCount":3000,"pondId":301020001},"5010547":{"id":5010547,"name":"buy_lure_crayfish01_7","mark":"","showStyle":3,"itemType":309,"goodsId":1030920400307,"costItem":101,"costCount":3000,"pondId":301020001},"5010548":{"id":5010548,"name":"buy_lure_worm01_1","mark":"","showStyle":3,"itemType":309,"goodsId":1030920300101,"costItem":101,"costCount":2500,"pondId":301020001},"5010549":{"id":5010549,"name":"buy_lure_worm01_2","mark":"","showStyle":3,"itemType":309,"goodsId":1030920300102,"costItem":101,"costCount":2500,"pondId":301020001},"5010550":{"id":5010550,"name":"buy_lure_worm01_3","mark":"","showStyle":3,"itemType":309,"goodsId":1030920300103,"costItem":101,"costCount":2500,"pondId":301020001},"5010551":{"id":5010551,"name":"buy_lure_worm01_4","mark":"","showStyle":3,"itemType":309,"goodsId":1030920300104,"costItem":101,"costCount":2500,"pondId":301020001},"5010552":{"id":5010552,"name":"buy_lure_worm01_5","mark":"","showStyle":3,"itemType":309,"goodsId":1030920300105,"costItem":101,"costCount":2500,"pondId":301020001},"5010553":{"id":5010553,"name":"buy_lure_worm01_6","mark":"","showStyle":3,"itemType":309,"goodsId":1030920300106,"costItem":101,"costCount":2500,"pondId":301020001},"5010554":{"id":5010554,"name":"buy_lure_worm01_7","mark":"","showStyle":3,"itemType":309,"goodsId":1030920300107,"costItem":101,"costCount":2500,"pondId":301020001},"5010709":{"id":5010709,"name":"buy_lure_frog01_1","mark":"","showStyle":3,"itemType":309,"goodsId":1030931000101,"costItem":101,"costCount":1000,"pondId":301020001},"5010710":{"id":5010710,"name":"buy_lure_frog01_2","mark":"","showStyle":3,"itemType":309,"goodsId":1030931000102,"costItem":101,"costCount":1000,"pondId":301020001},"5010711":{"id":5010711,"name":"buy_lure_frog01_3","mark":"","showStyle":3,"itemType":309,"goodsId":1030931000103,"costItem":101,"costCount":1000,"pondId":301020001},"5010712":{"id":5010712,"name":"buy_lure_frog01_4","mark":"","showStyle":3,"itemType":309,"goodsId":1030931000104,"costItem":101,"costCount":1000,"pondId":301020001},"5010713":{"id":5010713,"name":"buy_lure_frog01_5","mark":"","showStyle":3,"itemType":309,"goodsId":1030931000105,"costItem":101,"costCount":1000,"pondId":301020001},"5010714":{"id":5010714,"name":"buy_lure_frog01_6","mark":"","showStyle":3,"itemType":309,"goodsId":1030931000106,"costItem":101,"costCount":1000,"pondId":301020001},"5010715":{"id":5010715,"name":"buy_lure_frog01_7","mark":"","showStyle":3,"itemType":309,"goodsId":1030931000107,"costItem":101,"costCount":1000,"pondId":301020001},"5010737":{"id":5010737,"name":"buy_hook_sleeve_black01_1","mark":"","showStyle":3,"itemType":308,"goodsId":1030810200101,"costItem":101,"costCount":250,"pondId":301020001},"5010738":{"id":5010738,"name":"buy_hook_sleeve_black01_2","mark":"","showStyle":3,"itemType":308,"goodsId":1030810200102,"costItem":101,"costCount":280,"pondId":301020001},"5010739":{"id":5010739,"name":"buy_hook_sleeve_black01_3","mark":"","showStyle":3,"itemType":308,"goodsId":1030810200103,"costItem":101,"costCount":320,"pondId":301020001},"5010740":{"id":5010740,"name":"buy_hook_sleeve_black01_4","mark":"","showStyle":3,"itemType":308,"goodsId":1030810200104,"costItem":101,"costCount":360,"pondId":301020001},"5010741":{"id":5010741,"name":"buy_hook_sleeve_black01_5","mark":"","showStyle":3,"itemType":308,"goodsId":1030810200105,"costItem":101,"costCount":450,"pondId":301020001},"5010742":{"id":5010742,"name":"buy_hook_sleeve_black01_6","mark":"","showStyle":3,"itemType":308,"goodsId":1030810200106,"costItem":101,"costCount":520,"pondId":301020001},"5010743":{"id":5010743,"name":"buy_hook_sleeve_black01_7","mark":"","showStyle":3,"itemType":308,"goodsId":1030810200107,"costItem":101,"costCount":560,"pondId":301020001},"5010744":{"id":5010744,"name":"buy_hook_sleeve_black01_8","mark":"","showStyle":3,"itemType":308,"goodsId":1030810200108,"costItem":101,"costCount":580,"pondId":301020001},"5010745":{"id":5010745,"name":"buy_hook_fisheye01_1","mark":"","showStyle":3,"itemType":308,"goodsId":1030820200101,"costItem":101,"costCount":1900,"pondId":301020001},"5010746":{"id":5010746,"name":"buy_hook_fisheye01_2","mark":"","showStyle":3,"itemType":308,"goodsId":1030820200102,"costItem":101,"costCount":1950,"pondId":301020001},"5010747":{"id":5010747,"name":"buy_hook_fisheye01_3","mark":"","showStyle":3,"itemType":308,"goodsId":1030820200103,"costItem":101,"costCount":1980,"pondId":301020001},"5010748":{"id":5010748,"name":"buy_hook_fisheye01_4","mark":"","showStyle":3,"itemType":308,"goodsId":1030820200104,"costItem":101,"costCount":2060,"pondId":301020001},"5010749":{"id":5010749,"name":"buy_hook_fisheye01_5","mark":"","showStyle":3,"itemType":308,"goodsId":1030820200105,"costItem":101,"costCount":2080,"pondId":301020001},"5010750":{"id":5010750,"name":"buy_hook_fisheye01_6","mark":"","showStyle":3,"itemType":308,"goodsId":1030820200106,"costItem":101,"costCount":2090,"pondId":301020001},"5010751":{"id":5010751,"name":"buy_hook_fisheye01_7","mark":"","showStyle":3,"itemType":308,"goodsId":1030820200107,"costItem":101,"costCount":2100,"pondId":301020001},"5010752":{"id":5010752,"name":"buy_hook_fisheye01_8","mark":"","showStyle":3,"itemType":308,"goodsId":1030820200108,"costItem":101,"costCount":2150,"pondId":301020001},"5010753":{"id":5010753,"name":"buy_hook_head01_1","mark":"","showStyle":3,"itemType":308,"goodsId":1030820100101,"costItem":101,"costCount":1420,"pondId":301020001},"5010754":{"id":5010754,"name":"buy_hook_head01_2","mark":"","showStyle":3,"itemType":308,"goodsId":1030820100102,"costItem":101,"costCount":1440,"pondId":301020001},"5010755":{"id":5010755,"name":"buy_hook_head01_3","mark":"","showStyle":3,"itemType":308,"goodsId":1030820100103,"costItem":101,"costCount":1480,"pondId":301020001},"5010756":{"id":5010756,"name":"buy_hook_head01_4","mark":"","showStyle":3,"itemType":308,"goodsId":1030820100104,"costItem":101,"costCount":1520,"pondId":301020001},"5010757":{"id":5010757,"name":"buy_hook_head01_5","mark":"","showStyle":3,"itemType":308,"goodsId":1030820100105,"costItem":101,"costCount":1530,"pondId":301020001},"5010758":{"id":5010758,"name":"buy_hook_head01_6","mark":"","showStyle":3,"itemType":308,"goodsId":1030820100106,"costItem":101,"costCount":1560,"pondId":301020001},"5010759":{"id":5010759,"name":"buy_hook_head01_7","mark":"","showStyle":3,"itemType":308,"goodsId":1030820100107,"costItem":101,"costCount":1580,"pondId":301020001},"5010760":{"id":5010760,"name":"buy_hook_wacky01_1","mark":"","showStyle":3,"itemType":308,"goodsId":1030820400101,"costItem":101,"costCount":1750,"pondId":301020001},"5010761":{"id":5010761,"name":"buy_hook_wacky01_2","mark":"","showStyle":3,"itemType":308,"goodsId":1030820400102,"costItem":101,"costCount":1780,"pondId":301020001},"5010762":{"id":5010762,"name":"buy_hook_wacky01_3","mark":"","showStyle":3,"itemType":308,"goodsId":1030820400103,"costItem":101,"costCount":1790,"pondId":301020001},"5010763":{"id":5010763,"name":"buy_hook_wacky01_4","mark":"","showStyle":3,"itemType":308,"goodsId":1030820400104,"costItem":101,"costCount":1820,"pondId":301020001},"5010764":{"id":5010764,"name":"buy_hook_wacky01_5","mark":"","showStyle":3,"itemType":308,"goodsId":1030820400105,"costItem":101,"costCount":1840,"pondId":301020001},"5010765":{"id":5010765,"name":"buy_hook_wacky01_6","mark":"","showStyle":3,"itemType":308,"goodsId":1030820400106,"costItem":101,"costCount":1880,"pondId":301020001},"5010766":{"id":5010766,"name":"buy_hook_wacky01_7","mark":"","showStyle":3,"itemType":308,"goodsId":1030820400107,"costItem":101,"costCount":1900,"pondId":301020001},"5010767":{"id":5010767,"name":"buy_hook_offset01_1","mark":"","showStyle":3,"itemType":308,"goodsId":1030820300101,"costItem":101,"costCount":880,"pondId":301020001},"5010768":{"id":5010768,"name":"buy_hook_offset01_2","mark":"","showStyle":3,"itemType":308,"goodsId":1030820300102,"costItem":101,"costCount":940,"pondId":301020001},"5010769":{"id":5010769,"name":"buy_hook_offset01_3","mark":"","showStyle":3,"itemType":308,"goodsId":1030820300103,"costItem":101,"costCount":980,"pondId":301020001},"5010770":{"id":5010770,"name":"buy_hook_offset01_4","mark":"","showStyle":3,"itemType":308,"goodsId":1030820300104,"costItem":101,"costCount":1040,"pondId":301020001},"5010771":{"id":5010771,"name":"buy_hook_offset01_5","mark":"","showStyle":3,"itemType":308,"goodsId":1030820300105,"costItem":101,"costCount":1060,"pondId":301020001},"5010772":{"id":5010772,"name":"buy_hook_offset01_6","mark":"","showStyle":3,"itemType":308,"goodsId":1030820300106,"costItem":101,"costCount":1080,"pondId":301020001},"5010773":{"id":5010773,"name":"buy_hook_offset01_7","mark":"","showStyle":3,"itemType":308,"goodsId":1030820300107,"costItem":101,"costCount":1100,"pondId":301020001},"5010795":{"id":5010795,"name":"buy_hook_sleeve_gold01_1","mark":"","showStyle":3,"itemType":308,"goodsId":1030810200201,"costItem":101,"costCount":2860,"pondId":301020001},"5010796":{"id":5010796,"name":"buy_hook_sleeve_gold01_2","mark":"","showStyle":3,"itemType":308,"goodsId":1030810200202,"costItem":101,"costCount":2880,"pondId":301020001},"5010797":{"id":5010797,"name":"buy_hook_sleeve_gold01_3","mark":"","showStyle":3,"itemType":308,"goodsId":1030810200203,"costItem":101,"costCount":2920,"pondId":301020001},"5010798":{"id":5010798,"name":"buy_hook_sleeve_gold01_4","mark":"","showStyle":3,"itemType":308,"goodsId":1030810200204,"costItem":101,"costCount":2960,"pondId":301020001},"5010799":{"id":5010799,"name":"buy_hook_sleeve_gold01_5","mark":"","showStyle":3,"itemType":308,"goodsId":1030810200205,"costItem":101,"costCount":2980,"pondId":301020001},"5010800":{"id":5010800,"name":"buy_hook_sleeve_gold01_6","mark":"","showStyle":3,"itemType":308,"goodsId":1030810200206,"costItem":101,"costCount":3050,"pondId":301020001},"5010801":{"id":5010801,"name":"buy_hook_sleeve_gold01_7","mark":"","showStyle":3,"itemType":308,"goodsId":1030810200207,"costItem":101,"costCount":3080,"pondId":301020001},"5010802":{"id":5010802,"name":"buy_hook_sleeve_red01_1","mark":"","showStyle":3,"itemType":308,"goodsId":1030810200301,"costItem":101,"costCount":1420,"pondId":301020001},"5010803":{"id":5010803,"name":"buy_hook_sleeve_red01_2","mark":"","showStyle":3,"itemType":308,"goodsId":1030810200302,"costItem":101,"costCount":1440,"pondId":301020001},"5010804":{"id":5010804,"name":"buy_hook_sleeve_red01_3","mark":"","showStyle":3,"itemType":308,"goodsId":1030810200303,"costItem":101,"costCount":1480,"pondId":301020001},"5010805":{"id":5010805,"name":"buy_hook_sleeve_red01_4","mark":"","showStyle":3,"itemType":308,"goodsId":1030810200304,"costItem":101,"costCount":1520,"pondId":301020001},"5010806":{"id":5010806,"name":"buy_hook_sleeve_red01_5","mark":"","showStyle":3,"itemType":308,"goodsId":1030810200305,"costItem":101,"costCount":1530,"pondId":301020001},"5010807":{"id":5010807,"name":"buy_hook_sleeve_red01_6","mark":"","showStyle":3,"itemType":308,"goodsId":1030810200306,"costItem":101,"costCount":1560,"pondId":301020001},"5010808":{"id":5010808,"name":"buy_hook_sleeve_red01_7","mark":"","showStyle":3,"itemType":308,"goodsId":1030810200307,"costItem":101,"costCount":1580,"pondId":301020001},"5010809":{"id":5010809,"name":"buy_hook_sleeve_silver01_1","mark":"","showStyle":3,"itemType":308,"goodsId":1030810200401,"costItem":101,"costCount":2420,"pondId":301020001},"5010810":{"id":5010810,"name":"buy_hook_sleeve_silver01_2","mark":"","showStyle":3,"itemType":308,"goodsId":1030810200402,"costItem":101,"costCount":2450,"pondId":301020001},"5010811":{"id":5010811,"name":"buy_hook_sleeve_silver01_3","mark":"","showStyle":3,"itemType":308,"goodsId":1030810200403,"costItem":101,"costCount":2500,"pondId":301020001},"5010812":{"id":5010812,"name":"buy_hook_sleeve_silver01_4","mark":"","showStyle":3,"itemType":308,"goodsId":1030810200404,"costItem":101,"costCount":2580,"pondId":301020001},"5010813":{"id":5010813,"name":"buy_hook_sleeve_silver01_5","mark":"","showStyle":3,"itemType":308,"goodsId":1030810200405,"costItem":101,"costCount":2600,"pondId":301020001},"5010814":{"id":5010814,"name":"buy_hook_sleeve_silver01_6","mark":"","showStyle":3,"itemType":308,"goodsId":1030810200406,"costItem":101,"costCount":2640,"pondId":301020001},"5010815":{"id":5010815,"name":"buy_hook_sleeve_silver01_7","mark":"","showStyle":3,"itemType":308,"goodsId":1030810200407,"costItem":101,"costCount":2660,"pondId":301020001}}