{"1":{"id":1,"behaviourId":301030012,"actionId":102,"probWeight":30,"proportionMin":10,"proportionMax":20,"timeMin":400,"timeMax":800},"10":{"id":10,"behaviourId":301030015,"actionId":102,"probWeight":5,"proportionMin":10,"proportionMax":20,"timeMin":400,"timeMax":800},"11":{"id":11,"behaviourId":301030015,"actionId":103,"probWeight":70,"proportionMin":20,"proportionMax":30,"timeMin":600,"timeMax":900},"12":{"id":12,"behaviourId":301030015,"actionId":104,"probWeight":70,"proportionMin":20,"proportionMax":40,"timeMin":300,"timeMax":600},"13":{"id":13,"behaviourId":301030016,"actionId":102,"probWeight":0,"proportionMin":0,"proportionMax":0,"timeMin":0,"timeMax":0},"14":{"id":14,"behaviourId":301030016,"actionId":103,"probWeight":20,"proportionMin":20,"proportionMax":30,"timeMin":600,"timeMax":900},"15":{"id":15,"behaviourId":301030016,"actionId":104,"probWeight":80,"proportionMin":20,"proportionMax":40,"timeMin":300,"timeMax":600},"16":{"id":16,"behaviourId":301030017,"actionId":102,"probWeight":30,"proportionMin":10,"proportionMax":20,"timeMin":400,"timeMax":800},"17":{"id":17,"behaviourId":301030017,"actionId":103,"probWeight":70,"proportionMin":20,"proportionMax":30,"timeMin":600,"timeMax":900},"18":{"id":18,"behaviourId":301030017,"actionId":104,"probWeight":5,"proportionMin":20,"proportionMax":40,"timeMin":300,"timeMax":600},"19":{"id":19,"behaviourId":301030018,"actionId":102,"probWeight":30,"proportionMin":10,"proportionMax":20,"timeMin":400,"timeMax":800},"2":{"id":2,"behaviourId":301030012,"actionId":103,"probWeight":60,"proportionMin":20,"proportionMax":30,"timeMin":600,"timeMax":900},"20":{"id":20,"behaviourId":301030018,"actionId":103,"probWeight":40,"proportionMin":20,"proportionMax":30,"timeMin":600,"timeMax":900},"21":{"id":21,"behaviourId":301030018,"actionId":104,"probWeight":20,"proportionMin":20,"proportionMax":40,"timeMin":300,"timeMax":600},"22":{"id":22,"behaviourId":301030019,"actionId":102,"probWeight":10,"proportionMin":10,"proportionMax":20,"timeMin":400,"timeMax":800},"23":{"id":23,"behaviourId":301030019,"actionId":103,"probWeight":50,"proportionMin":20,"proportionMax":30,"timeMin":600,"timeMax":900},"24":{"id":24,"behaviourId":301030019,"actionId":104,"probWeight":30,"proportionMin":20,"proportionMax":40,"timeMin":300,"timeMax":600},"25":{"id":25,"behaviourId":301030020,"actionId":102,"probWeight":30,"proportionMin":10,"proportionMax":20,"timeMin":400,"timeMax":800},"26":{"id":26,"behaviourId":301030020,"actionId":103,"probWeight":80,"proportionMin":20,"proportionMax":30,"timeMin":600,"timeMax":900},"27":{"id":27,"behaviourId":301030020,"actionId":104,"probWeight":20,"proportionMin":20,"proportionMax":40,"timeMin":300,"timeMax":600},"28":{"id":28,"behaviourId":301030021,"actionId":102,"probWeight":10,"proportionMin":10,"proportionMax":20,"timeMin":400,"timeMax":800},"29":{"id":29,"behaviourId":301030021,"actionId":103,"probWeight":50,"proportionMin":20,"proportionMax":30,"timeMin":600,"timeMax":900},"3":{"id":3,"behaviourId":301030012,"actionId":104,"probWeight":20,"proportionMin":20,"proportionMax":40,"timeMin":300,"timeMax":600},"30":{"id":30,"behaviourId":301030021,"actionId":104,"probWeight":0,"proportionMin":0,"proportionMax":0,"timeMin":0,"timeMax":0},"31":{"id":31,"behaviourId":301030022,"actionId":102,"probWeight":20,"proportionMin":10,"proportionMax":20,"timeMin":400,"timeMax":800},"32":{"id":32,"behaviourId":301030022,"actionId":103,"probWeight":30,"proportionMin":20,"proportionMax":30,"timeMin":600,"timeMax":900},"33":{"id":33,"behaviourId":301030022,"actionId":104,"probWeight":0,"proportionMin":0,"proportionMax":0,"timeMin":0,"timeMax":0},"34":{"id":34,"behaviourId":301030023,"actionId":102,"probWeight":10,"proportionMin":20,"proportionMax":40,"timeMin":300,"timeMax":600},"35":{"id":35,"behaviourId":301030023,"actionId":103,"probWeight":5,"proportionMin":20,"proportionMax":30,"timeMin":600,"timeMax":900},"36":{"id":36,"behaviourId":301030023,"actionId":104,"probWeight":50,"proportionMin":20,"proportionMax":30,"timeMin":600,"timeMax":900},"4":{"id":4,"behaviourId":301030013,"actionId":102,"probWeight":70,"proportionMin":10,"proportionMax":20,"timeMin":400,"timeMax":800},"5":{"id":5,"behaviourId":301030013,"actionId":103,"probWeight":40,"proportionMin":20,"proportionMax":30,"timeMin":600,"timeMax":900},"6":{"id":6,"behaviourId":301030013,"actionId":104,"probWeight":0,"proportionMin":0,"proportionMax":0,"timeMin":0,"timeMax":0},"7":{"id":7,"behaviourId":301030014,"actionId":102,"probWeight":0,"proportionMin":10,"proportionMax":20,"timeMin":400,"timeMax":800},"8":{"id":8,"behaviourId":301030014,"actionId":103,"probWeight":70,"proportionMin":20,"proportionMax":30,"timeMin":600,"timeMax":900},"9":{"id":9,"behaviourId":301030014,"actionId":104,"probWeight":50,"proportionMin":20,"proportionMax":40,"timeMin":300,"timeMax":600}}